fileworker/__init__.py
fileworker-0.1.0.dist-info/METADATA
fileworker-0.1.0.dist-info/WHEEL
fileworker-0.1.0.dist-info/RECORD
