Metadata-Version: 2.1
Name: fileworker
Version: 0.1.0
Summary: Work with files
License: MIT
Author: Alexey Prikhodko
Author-email: alexeyayaya@gmail.com
Requires-Python: >=3.9,<4.0
Classifier: License :: OSI Approved :: MIT License
Classifier: Programming Language :: Python :: 3
Classifier: Programming Language :: Python :: 3.9
Classifier: Programming Language :: Python :: 3.10
Classifier: Programming Language :: Python :: 3.11
